Workbook

Sheet Resume
A1: ECRIN - Recette de thème
A2: Checklist de QA multi-onglets. Ouvre chaque onglet, remplis la colonne Statut via le dropdown, ajoute tes notes.
A4: Onglet | B4: Total tests | C4: OK | D4: KO | E4: A revoir | F4: Not tested
A5: Homepage | B5: 110 | C5: =COUNTIF('Homepage'!G2:G111,"OK") | D5: =COUNTIF('Homepage'!G2:G111,"KO") | E5: =COUNTIF('Homepage'!G2:G111,"A revoir") | F5: =COUNTIF('Homepage'!G2:G111,"Not tested")
A6: Global | B6: 47 | C6: =COUNTIF('Global'!G2:G48,"OK") | D6: =COUNTIF('Global'!G2:G48,"KO") | E6: =COUNTIF('Global'!G2:G48,"A revoir") | F6: =COUNTIF('Global'!G2:G48,"Not tested")
A7: Produit | B7: 46 | C7: =COUNTIF('Produit'!G2:G47,"OK") | D7: =COUNTIF('Produit'!G2:G47,"KO") | E7: =COUNTIF('Produit'!G2:G47,"A revoir") | F7: =COUNTIF('Produit'!G2:G47,"Not tested")
A8: Collection | B8: 17 | C8: =COUNTIF('Collection'!G2:G18,"OK") | D8: =COUNTIF('Collection'!G2:G18,"KO") | E8: =COUNTIF('Collection'!G2:G18,"A revoir") | F8: =COUNTIF('Collection'!G2:G18,"Not tested")
A9: Autres pages | B9: 43 | C9: =COUNTIF('Autres pages'!G2:G44,"OK") | D9: =COUNTIF('Autres pages'!G2:G44,"KO") | E9: =COUNTIF('Autres pages'!G2:G44,"A revoir") | F9: =COUNTIF('Autres pages'!G2:G44,"Not tested")
A10: Cross-cutting | B10: 53 | C10: =COUNTIF('Cross-cutting'!G2:G54,"OK") | D10: =COUNTIF('Cross-cutting'!G2:G54,"KO") | E10: =COUNTIF('Cross-cutting'!G2:G54,"A revoir") | F10: =COUNTIF('Cross-cutting'!G2:G54,"Not tested")
A11: Total | B11: 316 | C11: =SUM(C5:C10) | D11: =SUM(D5:D10) | E11: =SUM(E5:E10) | F11: =SUM(F5:F10)
A14: Legende
A15: Priorites:
A16: P0 | B16: Blocker - a fixer avant submission
A17: P1 | B17: Polish - recommande avant ship
A18: P2 | B18: Nice-to-have - si temps
A20: Statuts:
A21: OK | B21: Test passe, rien a signaler
A22: KO | B22: Test echoue, bug a fixer
A23: A revoir | B23: Comportement ambigu, discussion necessaire
A24: Not tested | B24: Pas encore verifie

Sheet Homepage
A1: ID | B1: Section | C1: Test | D1: Comportement attendu | E1: Priorite | F1: Device | G1: Statut | H1: Notes
A2: HERO-01 | B2: Hero | C2: Load image + focal point | D2: L'image hero s'affiche avec le focal point respecte (sujet pas coupe) | E2: P0 | F2: Both | G2: Not tested
A3: HERO-02 | B3: Hero | C3: Typography hierarchy | D3: Subheading 11px uppercase / Heading 72px Cormorant / Body 16px / CTAs 14px | E3: P1 | F3: Desktop | G3: Not tested
A4: HERO-03 | B4: Hero | C4: Entry animation on load | D4: Stagger: subheading -> heading -> text -> buttons (fade+translateY sur ~800ms) | E4: P1 | F4: Desktop | G4: Not tested
A5: HERO-04 | B5: Hero | C5: CTA1 'Shop the collection' link | D5: Navigue vers /collections/all | E5: P0 | F5: Both | G5: Not tested
A6: HERO-05 | B6: Hero | C6: CTA2 'The atelier' link | D6: Navigue vers /pages/about | E6: P0 | F6: Both | G6: Not tested
A7: HERO-06 | B7: Hero | C7: Buttons :hover | D7: Bg fade sur btn--filled-white, fill sur btn--outline-white (350ms ease-ecrin) | E7: P1 | F7: Desktop | G7: Not tested
A8: HERO-07 | B8: Hero | C8: Scroll indicator bounce | D8: Chevron anime bounce 2s infinite en bas du hero | E8: P2 | F8: Desktop | G8: Not tested
A9: HERO-08 | B9: Hero | C9: Parallax on scroll | D9: Image translate legerement au scroll si enable_parallax | E9: P2 | F9: Desktop | G9: Not tested
A10: HERO-09 | B10: Hero | C10: Mobile CTAs full-width stacked | D10: Les 2 CTAs font 100% de largeur, stack vertical, gap 12px, max-width 320px | E10: P1 | F10: Mobile | G10: Not tested
A11: HERO-10 | B11: Hero | C11: Mobile height | D11: Hero prend minimum 80vh pour impact premium | E11: P2 | F11: Mobile | G11: Not tested
A12: MARQ-01 | B12: Marquee | C12: Continuous scroll | D12: Track scroll horizontal 25s linear infinite, pas de glitch au loop | E12: P1 | F12: Both | G12: Not tested
A13: MARQ-02 | B13: Marquee | C13: Content visible | D13: Items texte + icone separator entre chaque, padding aere | E13: P1 | F13: Both | G13: Not tested
... A111: NL-08 | B111: Newsletter | C111: Mobile layout | D111: Input + button stack verticalement ou inline selon layout | E111: P1 | F111: Mobile | G111: Not tested

Sheet Global
A1: ID | B1: Section | C1: Test | D1: Comportement attendu | E1: Priorite | F1: Device | G1: Statut | H1: Notes
A2: ANN-01 | B2: Announcement bar | C2: Messages rotate | D2: 3 messages cyclent toutes les 5s (cycle total 15s) | E2: P1 | F2: Both | G2: Not tested
A3: ANN-02 | B3: Announcement bar | C3: Cross-fade (not hard-swap) | D3: Fade-in/out sur 5-8% du cycle, overlap visuel subtil | E3: P1 | F3: Both | G3: Not tested
A4: ANN-03 | B4: Announcement bar | C4: Close button works | D4: Clic X cache la bar, persistance sessionStorage | E4: P1 | F4: Both | G4: Not tested
A5: ANN-04 | B5: Announcement bar | C5: Link per message | D5: Clic message avec link navigue vers URL | E5: P2 | F5: Both | G5: Not tested
A6: ANN-05 | B6: Announcement bar | C6: Mobile wraps | D6: Message long wraps sur 2 lignes mobile sans overflow | E6: P1 | F6: Mobile | G6: Not tested
A7: ANN-06 | B7: Announcement bar | C7: Color scheme | D7: Applique color-scheme setting (default scheme-2) | E7: P2 | F7: Both | G7: Not tested
A8: HDR-01 | B8: Header | C8: Logo renders | D8: Logo text ou image selon config | E8: P0 | F8: Both | G8: Not tested
A9: HDR-02 | B9: Header | C9: Main menu visible | D9: Items linklist menu rendered | E9: P0 | F9: Both | G9: Not tested
A10: HDR-03 | B10: Header | C10: Mega-menu on hover | D10: Hover menu item avec sub-items -> dropdown s'ouvre | E10: P1 | F10: Desktop | G10: Not tested
A11: HDR-04 | B11: Header | C11: Search icon opens predictive | D11: Clic loupe -> panel predictive search slide-in | E11: P1 | F11: Both | G11: Not tested
A12: HDR-05 | B12: Header | C12: Predictive search suggestions | D12: Tape 'bea' -> suggestions products/articles/pages live | E12: P1 | F12: Both | G12: Not tested
A13: HDR-06 | B13: Header | C13: Account icon | D13: Clic -> /account si connecte, /account/login sinon | E13: P1 | F13: Both | G13: Not tested
... A48: FT-10 | B48: Footer | C48: Menu links | D48: Chaque link du linklist footer fonctionnel | E48: P1 | F48: Both | G48: Not tested

Sheet Produit
A1: ID | B1: Section | C1: Test | D1: Comportement attendu | E1: Priorite | F1: Device | G1: Statut | H1: Notes
A2: PROD-01 | B2: Main product gallery | C2: All media renders | D2: Images, video embed, 3D model_viewer dans la gallery | E2: P0 | F2: Both | G2: Not tested
A3: PROD-02 | B3: Main product gallery | C3: Thumbnail nav | D3: Clic thumbnail change main image | E3: P1 | F3: Both | G3: Not tested
A4: PROD-03 | B4: Main product gallery | C4: Zoom on hover/click | D4: Hover/click active zoom sur image principale | E4: P1 | F4: Desktop | G4: Not tested
A5: PROD-04 | B5: Main product gallery | C5: Video plays | D5: Click play sur media type video fonctionne | E5: P1 | F5: Both | G5: Not tested
A6: PROD-05 | B6: Main product gallery | C6: 3D model_viewer loads | D6: Si media type model, viewer charge avec controls orbit/zoom | E6: P1 | F6: Both | G6: Not tested
A7: PROD-06 | B7: Main product title | C7: Vendor line (if enabled) | D7: product.vendor en label small au-dessus du title | E7: P2 | F7: Both | G7: Not tested
A8: PROD-07 | B8: Main product title | C8: Title heading | D8: product.title en H1 taille configurable | E8: P0 | F8: Both | G8: Not tested
A9: PROD-08 | B9: Main product price | C9: Price + compare | D9: current_variant.price + compare_at_price barre si sale | E9: P0 | F9: Both | G9: Not tested
A10: PROD-09 | B10: Main product price | C10: Save badge (if sale) | D10: 'Save X EUR' badge si compare_at > price | E10: P1 | F10: Both | G10: Not tested
A11: PROD-10 | B11: Main product price | C11: Tax notice | D11: 'Tax included' ou 'Tax excluded' selon shop settings | E11: P2 | F11: Both | G11: Not tested
A12: PROD-11 | B12: Main product variants | C12: Swatch color | D12: Ronds de couleur avec swatch.color, active ring | E12: P0 | F12: Both | G12: Not tested
A13: PROD-12 | B13: Main product variants | C13: Swatch image | D13: Thumbnails swatch.image si variante a une image associee | E13: P1 | F13: Both | G13: Not tested
... A47: PROD-46 | B47: Guarantee multicolumn | C47: Mobile stack | D47: Stack 1 colonne sous 750px | E47: P1 | F47: Mobile | G47: Not tested

Sheet Collection
A1: ID | B1: Section | C1: Test | D1: Comportement attendu | E1: Priorite | F1: Device | G1: Statut | H1: Notes
A2: COLL-01 | B2: Collection banner | C2: Heading + description | D2: collection.title + collection.description | E2: P1 | F2: Both | G2: Not tested
A3: COLL-02 | B3: Collection banner | C3: Banner image | D3: Image de collection si uploadee | E3: P1 | F3: Both | G3: Not tested
A4: COLL-03 | B4: Collection toolbar | C4: Product count | D4: '42 products' texte dynamique | E4: P1 | F4: Both | G4: Not tested
A5: COLL-04 | B5: Collection toolbar | C5: Sort dropdown | D5: Sort by: best-selling, price-asc, price-desc, title, date | E5: P0 | F5: Both | G5: Not tested
A6: COLL-05 | B6: Collection toolbar | C6: Filter button (mobile) | D6: Bouton 'Filter' ouvre drawer sur mobile | E6: P0 | F6: Mobile | G6: Not tested
A7: COLL-06 | B7: Collection filters | C7: Filters sidebar desktop | D7: Sidebar avec groupes: type, price, color, size | E7: P0 | F7: Desktop | G7: Not tested
A8: COLL-07 | B8: Collection filters | C8: Collapsible groups | D8: Chaque groupe ouvre/ferme au clic | E8: P1 | F8: Both | G8: Not tested
A9: COLL-08 | B9: Collection filters | C9: Apply filter updates grid | D9: Clic filtre met a jour URL ?filter.v.option.color=... | E9: P0 | F9: Both | G9: Not tested
A10: COLL-09 | B10: Collection filters | C10: Clear all filters | D10: Bouton 'Clear all' reset et retire tous les filtres | E10: P1 | F10: Both | G10: Not tested
A11: COLL-10 | B11: Collection filters | C11: Active filters pills | D11: Pills au-dessus du grid avec X pour retirer filtre | E11: P1 | F11: Both | G11: Not tested
A12: COLL-11 | B12: Collection grid | C12: Cards render | D12: Grid 4/3/2/1 colonnes responsive | E12: P0 | F12: Both | G12: Not tested
A13: COLL-12 | B13: Collection grid | C13: Card swatches | D13: swatch.color et swatch.image visibles sur cards | E13: P1 | F13: Both | G13: Not tested
... A18: COLL-17 | B18: Collection mobile filter drawer | C18: Drawer UX | D18: Slide-in lateral, contenu scrollable, footer avec 'Apply' sticky | E18: P1 | F18: Mobile | G18: Not tested

Sheet Autres pages
A1: ID | B1: Section | C1: Test | D1: Comportement attendu | E1: Priorite | F1: Device | G1: Statut | H1: Notes
A2: CART-01 | B2: Cart page | C2: Line items list | D2: Tableau items avec thumbnail + title + variant + qty + price + remove | E2: P0 | F2: Both | G2: Not tested
A3: CART-02 | B3: Cart page | C3: Quantity update | D3: Input quantity met a jour via form submit ou ajax | E3: P0 | F3: Both | G3: Not tested
A4: CART-03 | B4: Cart page | C4: Remove item | D4: Clic remove supprime le line item | E4: P0 | F4: Both | G4: Not tested
A5: CART-04 | B5: Cart page | C5: Note textarea | D5: Cart note visible si enabled | E5: P1 | F5: Both | G5: Not tested
A6: CART-05 | B6: Cart page | C6: Gift wrap option | D6: Upsell gift wrap avec ajout product | E6: P1 | F6: Both | G6: Not tested
A7: CART-06 | B7: Cart page | C7: Subtotal + checkout | D7: Subtotal formatee + checkout button | E7: P0 | F7: Both | G7: Not tested
A8: CART-07 | B8: Cart page | C8: Continue shopping link | D8: Link vers /collections/all | E8: P1 | F8: Both | G8: Not tested
A9: CART-08 | B9: Cart page | C9: Empty state premium | D9: Meme empty state que cart-drawer (icon + heading + CTA) | E9: P1 | F9: Both | G9: Not tested
A10: CART-09 | B10: Cart page | C10: Shipping calculator | D10: Si enabled, calculateur zip code/country | E10: P2 | F10: Both | G10: Not tested
A11: CART-10 | B11: Cart page | C11: Dynamic checkout | D11: Shop Pay / PayPal buttons rendus | E11: P0 | F11: Both | G11: Not tested
A12: SRCH-01 | B12: Search predictive | C12: Opens on focus | D12: Input focus header ouvre panel predictive | E12: P1 | F12: Both | G12: Not tested
A13: SRCH-02 | B13: Search predictive | C13: Results live | D13: Tape text -> suggestions products/pages/articles updatees | E13: P1 | F13: Both | G13: Not tested
... A44: PWD-05 | B44: Password page | C44: Social icons | D44: Icons Instagram etc pour suivre le launch | E44: P2 | F44: Both | G44: Not tested

Sheet Cross-cutting
A1: ID | B1: Section | C1: Test | D1: Comportement attendu | E1: Priorite | F1: Device | G1: Statut | H1: Notes
A2: PERF-01 | B2: Performance | C2: Lighthouse perf >= 60 homepage mobile | D2: Score (p*31 + c*33 + h*13) / 77 >= 60 | E2: P0 | F2: Mobile | G2: Not tested
A3: PERF-02 | B3: Performance | C3: Lighthouse perf >= 60 collection mobile | D3: Score >= 60 sur /collections/all | E3: P0 | F3: Mobile | G3: Not tested
A4: PERF-03 | B4: Performance | C4: Lighthouse perf >= 60 product mobile | D4: Score >= 60 sur /products/X | E4: P0 | F4: Mobile | G4: Not tested
A5: PERF-04 | B5: Performance | C5: Images width+height | D5: Tous img avec attributes width et height pour eviter CLS | E5: P1 | F5: Both | G5: Not tested
A6: PERF-05 | B6: Performance | C6: Lazy loading below fold | D6: loading=lazy sur images sous le fold | E6: P1 | F6: Both | G6: Not tested
A7: PERF-06 | B7: Performance | C7: No parser-blocking JS | D7: Tous <script> avec defer ou async | E7: P1 | F7: Both | G7: Not tested
A8: PERF-07 | B8: Performance | C8: Critical CSS inline | D8: Styles above-fold inlines dans theme.liquid | E8: P2 | F8: Both | G8: Not tested
A9: PERF-08 | B9: Performance | C9: No external non-Shopify assets | D9: 0 requests vers CDN tiers non approuves | E9: P1 | F9: Both | G9: Not tested
A10: PERF-09 | B10: Performance | C10: Responsive srcset | D10: Images utilisent image_tag avec widths+sizes | E10: P1 | F10: Both | G10: Not tested
A11: A11Y-01 | B11: Accessibility | C11: Lighthouse a11y >= 90 homepage | D11: Score >= 90 via Lighthouse | E11: P0 | F11: Both | G11: Not tested
A12: A11Y-02 | B12: Accessibility | C12: Lighthouse a11y >= 90 collection | D12: Score >= 90 | E12: P0 | F12: Both | G12: Not tested
A13: A11Y-03 | B13: Accessibility | C13: Lighthouse a11y >= 90 product | D13: Score >= 90 | E13: P0 | F13: Both | G13: Not tested
... A54: CODE-08 | B54: Code quality | C54: 0 brand references | D54: Pas de 'Dawn', 'Publisher' ou noms de themes concurrents | E54: P0 | F54: Both | G54: Not tested
